game_sdk/__init__.py
game_sdk/game/README.md
game_sdk/game/__init__.py
game_sdk/game/agent.py
game_sdk/game/api.py
game_sdk/game/api_v2.py
game_sdk/game/chat_agent.py
game_sdk/game/custom_types.py
game_sdk/game/worker.py
game_sdk/hosted_game/README.md
game_sdk/hosted_game/__init__.py
game_sdk/hosted_game/agent.py
game_sdk/hosted_game/sdk.py
game_sdk/hosted_game/functions/__init__.py
game_sdk/hosted_game/functions/discord.py
game_sdk/hosted_game/functions/farcaster.py
game_sdk/hosted_game/functions/telegram.py
game_sdk-0.1.4.dist-info/METADATA
game_sdk-0.1.4.dist-info/WHEEL
game_sdk-0.1.4.dist-info/licenses/LICENSE
game_sdk-0.1.4.dist-info/RECORD
